setup.py
freedomsponsors/__init__.py
freedomsponsors/freedomsponsors_trac.py
freedomsponsors_trac_plugin.egg-info/PKG-INFO
freedomsponsors_trac_plugin.egg-info/SOURCES.txt
freedomsponsors_trac_plugin.egg-info/dependency_links.txt
freedomsponsors_trac_plugin.egg-info/entry_points.txt
freedomsponsors_trac_plugin.egg-info/not-zip-safe
freedomsponsors_trac_plugin.egg-info/top_level.txt