Metadata-Version: 1.0
Name: freedomsponsors-trac-plugin
Version: 0.1
Summary: FreedomSponsors Trac plugin
Home-page: http://github.com/iurisilvio/freedomsponsors-trac-plugin
Author: Iuri de Silvio
Author-email: iurisilvio@gmail.com
License: MIT
Keywords: trac plugin
Platform: UNKNOWN
